{
    "1683733844469267:44389": {
        "IResourceController": {
            "public": {
                "path": "Cloud VFX Resources/VFX",
                "hash": "2ed51057f3fcf0daf2f45089eb67c72e"
            }
        }
    },
    "1683733844470360:44390": {
        "IResourceController": {
            "name": "VFX",
            "type": 0,
            "subtype": -1,
            "dependency": 0,
            "hidden": false,
            "publicId": "1683733844469267:44389",
            "resources": []
        }
    }
}
